braintumor_model_package/.DS_Store
braintumor_model_package/VERSION
braintumor_model_package/__init__.py
braintumor_model_package/config/__init__.py
braintumor_model_package/config/core.py
braintumor_model_package/config.yml
braintumor_model_package/data_processing/__init__.py
braintumor_model_package/data_processing/data_manager.py
braintumor_model_package/data_processing/preprocessor.py
braintumor_model_package/datasets/.DS_Store
braintumor_model_package/datasets/__init__.py
braintumor_model_package/datasets/braintumor-data/.DS_Store
braintumor_model_package/datasets/braintumor-data/test_data/.DS_Store
braintumor_model_package/datasets/braintumor-data/test_data/Te-gl_0010.jpg
braintumor_model_package/datasets/braintumor-data/test_data/Te-gl_0011.jpg
braintumor_model_package/datasets/braintumor-data/test_data/Te-gl_0012.jpg
braintumor_model_package/datasets/braintumor-data/test_data/Te-gl_0013.jpg
braintumor_model_package/datasets/braintumor-data/test_data/Te-gl_0014.jpg
braintumor_model_package/datasets/braintumor-data/test_data/Te-gl_0015.jpg
braintumor_model_package/datasets/braintumor-data/test_data/Te-me_0016.jpg
braintumor_model_package/datasets/braintumor-data/test_data/Te-me_0017.jpg
braintumor_model_package/datasets/braintumor-data/test_data/Te-me_0018.jpg
braintumor_model_package/datasets/braintumor-data/test_data/Te-me_0019.jpg
braintumor_model_package/datasets/braintumor-data/test_data/Te-me_0020.jpg
braintumor_model_package/datasets/braintumor-data/test_data/Te-no_0021.jpg
braintumor_model_package/datasets/braintumor-data/test_data/Te-no_0022.jpg
braintumor_model_package/datasets/braintumor-data/test_data/Te-no_0023.jpg
braintumor_model_package/datasets/braintumor-data/test_data/Te-pi_0014.jpg
braintumor_model_package/datasets/braintumor-data/test_data/Te-pi_0015.jpg
braintumor_model_package/datasets/braintumor-data/test_data/Te-pi_0016.jpg
braintumor_model_package/model.py
braintumor_model_package/predict.py
braintumor_model_package/train_model.py
braintumor_model_package-0.2.0.dist-info/METADATA
braintumor_model_package-0.2.0.dist-info/WHEEL
braintumor_model_package-0.2.0.dist-info/RECORD
