Metadata-Version: 2.1
Name: braintumor-model-package
Version: 0.2.0
Summary: A brain tumor model package
Author: chibuikeeugene
Author-email: chibuikeeugene@gmail.com
Requires-Python: >=3.10,<4.0
Classifier: Programming Language :: Python :: 3
Classifier: Programming Language :: Python :: 3.10
Classifier: Programming Language :: Python :: 3.11
Classifier: Programming Language :: Python :: 3.12
Requires-Dist: kaggle (>=1.6.14,<2.0.0)
Requires-Dist: loguru (>=0.7.2,<0.8.0)
Requires-Dist: pandas (>=2.2.2,<3.0.0)
Requires-Dist: pydantic (>=2.7.1,<3.0.0)
Requires-Dist: scikit-learn (>=1.4.2,<2.0.0)
Requires-Dist: strictyaml (>=1.7.3,<2.0.0)
Requires-Dist: tensorflow (>=2.16.1,<3.0.0)
